LICENSE
MANIFEST.in
README.md
VERSION
setup.py
src/sat_mapping/__init__.py
src/sat_mapping/Fetch/Fetch.py
src/sat_mapping/Fetch/__init__.py
src/sat_mapping/FolderData/Folder.py
src/sat_mapping/FolderData/__init__.py
src/sat_mapping/Lib/__init__.py
src/sat_mapping/Lib/gsutil/CHANGES.md
src/sat_mapping/Lib/gsutil/CHECKSUM
src/sat_mapping/Lib/gsutil/CONTRIBUTING.md
src/sat_mapping/Lib/gsutil/LICENSE
src/sat_mapping/Lib/gsutil/README.md
src/sat_mapping/Lib/gsutil/VERSION
src/sat_mapping/Lib/gsutil/gsutil
src/sat_mapping/Lib/gsutil/gsutil.py
src/sat_mapping/Lib/gsutil/setup.py
src/sat_mapping/Lib/gsutil/gslib/README
src/sat_mapping/Lib/gsutil/gslib/__init__.py
src/sat_mapping/Lib/gsutil/gslib/__main__.py
src/sat_mapping/Lib/gsutil/gslib/boto_resumable_upload.py
src/sat_mapping/Lib/gsutil/gslib/boto_translation.py
src/sat_mapping/Lib/gsutil/gslib/bucket_listing_ref.py
src/sat_mapping/Lib/gsutil/gslib/cloud_api.py
src/sat_mapping/Lib/gsutil/gslib/cloud_api_delegator.py
src/sat_mapping/Lib/gsutil/gslib/command.py
src/sat_mapping/Lib/gsutil/gslib/command_argument.py
src/sat_mapping/Lib/gsutil/gslib/command_runner.py
src/sat_mapping/Lib/gsutil/gslib/context_config.py
src/sat_mapping/Lib/gsutil/gslib/cred_types.py
src/sat_mapping/Lib/gsutil/gslib/cs_api_map.py
src/sat_mapping/Lib/gsutil/gslib/daisy_chain_wrapper.py
src/sat_mapping/Lib/gsutil/gslib/devshell_auth_plugin.py
src/sat_mapping/Lib/gsutil/gslib/discard_messages_queue.py
src/sat_mapping/Lib/gsutil/gslib/exception.py
src/sat_mapping/Lib/gsutil/gslib/file_part.py
src/sat_mapping/Lib/gsutil/gslib/gcs_json_api.py
src/sat_mapping/Lib/gsutil/gslib/gcs_json_credentials.py
src/sat_mapping/Lib/gsutil/gslib/gcs_json_media.py
src/sat_mapping/Lib/gsutil/gslib/help_provider.py
src/sat_mapping/Lib/gsutil/gslib/iamcredentials_api.py
src/sat_mapping/Lib/gsutil/gslib/impersonation_credentials.py
src/sat_mapping/Lib/gsutil/gslib/kms_api.py
src/sat_mapping/Lib/gsutil/gslib/lazy_wrapper.py
src/sat_mapping/Lib/gsutil/gslib/metrics.py
src/sat_mapping_cyborg_ai.egg-info/PKG-INFO
src/sat_mapping_cyborg_ai.egg-info/SOURCES.txt
src/sat_mapping_cyborg_ai.egg-info/dependency_links.txt
src/sat_mapping_cyborg_ai.egg-info/requires.txt
src/sat_mapping_cyborg_ai.egg-info/top_level.txt