Metadata-Version: 2.1
Name: sat-mapping-cyborg-ai
Version: 0.0.37
Summary: A package to fetch sentinel 2 Satellite data from Google.
Home-page: https://github.com/iklelukas/sat_mapping
Author: Lukas Ikle
Author-email: lukas.ikle@itweet.ch
License: UNKNOWN
Project-URL: Bug Tracker, https://github.com/iklelukas/sat_mapping/issues
Platform: UNKNOWN
Classifier: Programming Language :: Python :: 3
Classifier: License :: OSI Approved :: MIT License
Classifier: Operating System :: OS Independent
Requires-Python: >=3.6
License-File: LICENSE
